[
  {
    "name": "BTC",
    "price": 103784,
    "change": 2.69124
  },
  {
    "name": "ETH",
    "price": 3431.2,
    "change": 6.20399
  },
  {
    "name": "USDT",
    "price": 1.0,
    "change": 0.00615
  },
  {
    "name": "XRP",
    "price": 2.35,
    "change": 6.23394
  },
  {
    "name": "BNB",
    "price": 958.55,
    "change": 2.7948
  },
  {
    "name": "SOL",
    "price": 162.62,
    "change": 5.09324
  },
  {
    "name": "USDC",
    "price": 0.999803,
    "change": 0.0004
  },
  {
    "name": "STETH",
    "price": 3438.28,
    "change": 6.23588
  },
  {
    "name": "TRX",
    "price": 0.289192,
    "change": 1.43748
  },
  {
    "name": "DOGE",
    "price": 0.167711,
    "change": 2.91914
  }
]