[
  {
    "name": "BTC",
    "price": 114023,
    "change": -1.06116
  },
  {
    "name": "ETH",
    "price": 4105.25,
    "change": -2.56074
  },
  {
    "name": "USDT",
    "price": 1.0,
    "change": -0.006
  },
  {
    "name": "XRP",
    "price": 2.63,
    "change": -0.47854
  },
  {
    "name": "BNB",
    "price": 1142.76,
    "change": -0.20615
  },
  {
    "name": "SOL",
    "price": 201.68,
    "change": -1.05582
  },
  {
    "name": "USDC",
    "price": 0.9999,
    "change": 0.01105
  },
  {
    "name": "STETH",
    "price": 4104.06,
    "change": -2.56646
  },
  {
    "name": "DOGE",
    "price": 0.199972,
    "change": -3.477
  },
  {
    "name": "TRX",
    "price": 0.299166,
    "change": -0.61309
  }
]