[
  {
    "name": "BTC",
    "price": 91568,
    "change": -2.20831
  },
  {
    "name": "ETH",
    "price": 3216.56,
    "change": -5.3359
  },
  {
    "name": "USDT",
    "price": 1.0,
    "change": -0.00263
  },
  {
    "name": "XRP",
    "price": 2.02,
    "change": -3.25385
  },
  {
    "name": "BNB",
    "price": 880.02,
    "change": -3.05756
  },
  {
    "name": "USDC",
    "price": 0.999853,
    "change": -0.00627
  },
  {
    "name": "SOL",
    "price": 135.16,
    "change": -3.91999
  },
  {
    "name": "STETH",
    "price": 3216.43,
    "change": -5.35494
  },
  {
    "name": "TRX",
    "price": 0.280617,
    "change": 0.3371
  },
  {
    "name": "DOGE",
    "price": 0.139688,
    "change": -5.94386
  }
]