[
  {
    "name": "BTC",
    "price": 79980,
    "change": -1.65433
  },
  {
    "name": "ETH",
    "price": 2289.47,
    "change": -2.3952
  },
  {
    "name": "USDT",
    "price": 0.999832,
    "change": 0.00034
  },
  {
    "name": "BNB",
    "price": 644.29,
    "change": -0.52052
  },
  {
    "name": "XRP",
    "price": 1.39,
    "change": -2.55008
  },
  {
    "name": "USDC",
    "price": 0.999638,
    "change": -0.01605
  },
  {
    "name": "SOL",
    "price": 88.22,
    "change": -0.81259
  },
  {
    "name": "TRX",
    "price": 0.347929,
    "change": 0.40959
  },
  {
    "name": "FIGR_HELOC",
    "price": 1.006,
    "change": -1.36408
  },
  {
    "name": "DOGE",
    "price": 0.107863,
    "change": -4.06602
  }
]