[
  {
    "name": "BTC",
    "price": 91103,
    "change": 0.27282
  },
  {
    "name": "ETH",
    "price": 3026.33,
    "change": 1.24688
  },
  {
    "name": "USDT",
    "price": 1.0,
    "change": -0.0251
  },
  {
    "name": "XRP",
    "price": 2.19,
    "change": -0.55348
  },
  {
    "name": "BNB",
    "price": 886.65,
    "change": 1.4947
  },
  {
    "name": "SOL",
    "price": 137.45,
    "change": 1.32729
  },
  {
    "name": "USDC",
    "price": 0.999728,
    "change": -0.00766
  },
  {
    "name": "TRX",
    "price": 0.282239,
    "change": 0.38815
  },
  {
    "name": "STETH",
    "price": 3023.95,
    "change": 1.25081
  },
  {
    "name": "DOGE",
    "price": 0.149217,
    "change": 0.76058
  }
]