[
  {
    "name": "BTC",
    "price": 88296,
    "change": 0.02075
  },
  {
    "name": "ETH",
    "price": 2978.26,
    "change": -0.27711
  },
  {
    "name": "USDT",
    "price": 0.999742,
    "change": 0.02106
  },
  {
    "name": "BNB",
    "price": 852.24,
    "change": -0.42876
  },
  {
    "name": "XRP",
    "price": 1.93,
    "change": 1.25655
  },
  {
    "name": "USDC",
    "price": 0.999916,
    "change": 0.00753
  },
  {
    "name": "SOL",
    "price": 126.07,
    "change": -0.68208
  },
  {
    "name": "TRX",
    "price": 0.280271,
    "change": -0.03951
  },
  {
    "name": "STETH",
    "price": 2976.04,
    "change": -0.38001
  },
  {
    "name": "DOGE",
    "price": 0.13218,
    "change": -0.31755
  }
]