[
  {
    "name": "BTC",
    "price": 87002,
    "change": 2.58393
  },
  {
    "name": "ETH",
    "price": 2804.11,
    "change": 1.04394
  },
  {
    "name": "USDT",
    "price": 0.999816,
    "change": 0.02126
  },
  {
    "name": "XRP",
    "price": 2.05,
    "change": 5.36549
  },
  {
    "name": "BNB",
    "price": 847.43,
    "change": 1.529
  },
  {
    "name": "USDC",
    "price": 0.99961,
    "change": -0.01177
  },
  {
    "name": "SOL",
    "price": 131.17,
    "change": 2.92521
  },
  {
    "name": "TRX",
    "price": 0.274725,
    "change": 0.14339
  },
  {
    "name": "STETH",
    "price": 2802.83,
    "change": 1.14692
  },
  {
    "name": "DOGE",
    "price": 0.145613,
    "change": 3.86852
  }
]