[
  {
    "name": "BTC",
    "price": 100683,
    "change": -2.04456
  },
  {
    "name": "ETH",
    "price": 3276.25,
    "change": -3.15664
  },
  {
    "name": "USDT",
    "price": 0.999597,
    "change": -0.0366
  },
  {
    "name": "XRP",
    "price": 2.18,
    "change": -5.0438
  },
  {
    "name": "BNB",
    "price": 949.24,
    "change": -0.34877
  },
  {
    "name": "SOL",
    "price": 154.03,
    "change": -3.14117
  },
  {
    "name": "USDC",
    "price": 0.999703,
    "change": -0.00989
  },
  {
    "name": "STETH",
    "price": 3275.74,
    "change": -3.18411
  },
  {
    "name": "TRX",
    "price": 0.285122,
    "change": -0.65099
  },
  {
    "name": "DOGE",
    "price": 0.164298,
    "change": 0.87244
  }
]