[
  {
    "name": "BTC",
    "price": 95132,
    "change": -0.14537
  },
  {
    "name": "ETH",
    "price": 3334.86,
    "change": 0.54727
  },
  {
    "name": "USDT",
    "price": 0.999614,
    "change": 0.00125
  },
  {
    "name": "BNB",
    "price": 950.11,
    "change": -0.04252
  },
  {
    "name": "XRP",
    "price": 2.06,
    "change": -0.79361
  },
  {
    "name": "SOL",
    "price": 142.03,
    "change": -1.2327
  },
  {
    "name": "USDC",
    "price": 0.999617,
    "change": -0.02124
  },
  {
    "name": "TRX",
    "price": 0.318766,
    "change": 1.28653
  },
  {
    "name": "STETH",
    "price": 3335.24,
    "change": 0.59152
  },
  {
    "name": "DOGE",
    "price": 0.136795,
    "change": -1.33864
  }
]