[
  {
    "name": "BTC",
    "price": 117427,
    "change": -0.04327
  },
  {
    "name": "ETH",
    "price": 2936.65,
    "change": -0.27515
  },
  {
    "name": "XRP",
    "price": 2.73,
    "change": 1.90643
  },
  {
    "name": "USDT",
    "price": 1.0,
    "change": -0.00776
  },
  {
    "name": "BNB",
    "price": 684.37,
    "change": -0.16061
  },
  {
    "name": "SOL",
    "price": 160.35,
    "change": -0.38288
  },
  {
    "name": "USDC",
    "price": 0.999804,
    "change": -0.01609
  },
  {
    "name": "DOGE",
    "price": 0.197373,
    "change": -0.7329
  },
  {
    "name": "TRX",
    "price": 0.302008,
    "change": 0.95823
  },
  {
    "name": "STETH",
    "price": 2935.29,
    "change": -0.2635
  }
]