[
  {
    "name": "BTC",
    "price": 59623,
    "change": 0.25879
  },
  {
    "name": "ETH",
    "price": 1573.0,
    "change": 0.56815
  },
  {
    "name": "USDT",
    "price": 0.998553,
    "change": 0.01362
  },
  {
    "name": "BNB",
    "price": 565.57,
    "change": 1.94352
  },
  {
    "name": "USDC",
    "price": 0.999715,
    "change": -0.00187
  },
  {
    "name": "XRP",
    "price": 1.048,
    "change": 1.2372
  },
  {
    "name": "SOL",
    "price": 73.01,
    "change": 9.94074
  },
  {
    "name": "TRX",
    "price": 0.320169,
    "change": -1.03602
  },
  {
    "name": "FIGR_HELOC",
    "price": 1.016,
    "change": -1.18796
  },
  {
    "name": "HYPE",
    "price": 64.8,
    "change": 1.53717
  }
]