[
  {
    "name": "BTC",
    "price": 86726,
    "change": 0.25214
  },
  {
    "name": "ETH",
    "price": 2913.98,
    "change": 3.11729
  },
  {
    "name": "USDT",
    "price": 0.9995,
    "change": -0.01554
  },
  {
    "name": "BNB",
    "price": 836.29,
    "change": 0.58617
  },
  {
    "name": "XRP",
    "price": 1.83,
    "change": -0.63564
  },
  {
    "name": "USDC",
    "price": 0.999922,
    "change": 0.00519
  },
  {
    "name": "SOL",
    "price": 122.62,
    "change": -0.04146
  },
  {
    "name": "TRX",
    "price": 0.279247,
    "change": 0.68134
  },
  {
    "name": "STETH",
    "price": 2915.09,
    "change": 3.15773
  },
  {
    "name": "DOGE",
    "price": 0.125517,
    "change": 0.97093
  }
]