[
  {
    "name": "BTC",
    "price": 111215,
    "change": -1.90629
  },
  {
    "name": "ETH",
    "price": 3935.84,
    "change": -2.14297
  },
  {
    "name": "USDT",
    "price": 1.0,
    "change": -0.01989
  },
  {
    "name": "XRP",
    "price": 2.59,
    "change": -1.81883
  },
  {
    "name": "BNB",
    "price": 1116.63,
    "change": -0.00623
  },
  {
    "name": "SOL",
    "price": 195.85,
    "change": 0.05594
  },
  {
    "name": "USDC",
    "price": 0.999808,
    "change": -0.00741
  },
  {
    "name": "STETH",
    "price": 3934.81,
    "change": -2.1828
  },
  {
    "name": "DOGE",
    "price": 0.192737,
    "change": -0.80226
  },
  {
    "name": "TRX",
    "price": 0.297216,
    "change": -0.11149
  }
]