[
  {
    "name": "BTC",
    "price": 109685,
    "change": 2.4489
  },
  {
    "name": "ETH",
    "price": 2562.24,
    "change": 2.60614
  },
  {
    "name": "USDT",
    "price": 1.0,
    "change": 0.01564
  },
  {
    "name": "XRP",
    "price": 2.34,
    "change": 2.0261
  },
  {
    "name": "BNB",
    "price": 674.58,
    "change": 1.83658
  },
  {
    "name": "SOL",
    "price": 177.05,
    "change": 3.06779
  },
  {
    "name": "USDC",
    "price": 0.999711,
    "change": -0.00779
  },
  {
    "name": "DOGE",
    "price": 0.226118,
    "change": 3.33298
  },
  {
    "name": "ADA",
    "price": 0.765008,
    "change": 3.94402
  },
  {
    "name": "TRX",
    "price": 0.273638,
    "change": 0.77137
  }
]