[
  {
    "name": "BTC",
    "price": 104479,
    "change": -2.86514
  },
  {
    "name": "ETH",
    "price": 2502.4,
    "change": -5.23813
  },
  {
    "name": "USDT",
    "price": 1.0,
    "change": -0.01336
  },
  {
    "name": "XRP",
    "price": 2.18,
    "change": -4.93713
  },
  {
    "name": "BNB",
    "price": 645.94,
    "change": -1.82353
  },
  {
    "name": "SOL",
    "price": 147.53,
    "change": -6.00897
  },
  {
    "name": "USDC",
    "price": 0.999708,
    "change": -0.00978
  },
  {
    "name": "TRX",
    "price": 0.274785,
    "change": -2.38214
  },
  {
    "name": "DOGE",
    "price": 0.168049,
    "change": -5.57135
  },
  {
    "name": "STETH",
    "price": 2499.25,
    "change": -5.32785
  }
]