[
  {
    "name": "BTC",
    "price": 104651,
    "change": -2.65595
  },
  {
    "name": "ETH",
    "price": 3504.28,
    "change": -5.53426
  },
  {
    "name": "USDT",
    "price": 0.999858,
    "change": -0.02234
  },
  {
    "name": "XRP",
    "price": 2.27,
    "change": -5.16071
  },
  {
    "name": "BNB",
    "price": 952.09,
    "change": -7.38769
  },
  {
    "name": "SOL",
    "price": 158.56,
    "change": -9.71351
  },
  {
    "name": "USDC",
    "price": 0.999805,
    "change": 0.00634
  },
  {
    "name": "STETH",
    "price": 3512.8,
    "change": -5.37845
  },
  {
    "name": "TRX",
    "price": 0.28156,
    "change": -3.9716
  },
  {
    "name": "DOGE",
    "price": 0.164689,
    "change": -4.55654
  }
]