[
  {
    "name": "BTC",
    "price": 114281,
    "change": 1.27555
  },
  {
    "name": "ETH",
    "price": 3498.77,
    "change": 2.43661
  },
  {
    "name": "XRP",
    "price": 2.93,
    "change": 4.52487
  },
  {
    "name": "USDT",
    "price": 0.999952,
    "change": 0.02575
  },
  {
    "name": "BNB",
    "price": 752.13,
    "change": 1.97616
  },
  {
    "name": "SOL",
    "price": 161.9,
    "change": 1.79966
  },
  {
    "name": "USDC",
    "price": 0.999703,
    "change": 0.00022
  },
  {
    "name": "STETH",
    "price": 3491.73,
    "change": 2.47273
  },
  {
    "name": "TRX",
    "price": 0.327041,
    "change": 1.42312
  },
  {
    "name": "DOGE",
    "price": 0.19916,
    "change": 2.80408
  }
]