[
  {
    "name": "BTC",
    "price": 87608,
    "change": -0.2501
  },
  {
    "name": "ETH",
    "price": 2931.73,
    "change": -0.53052
  },
  {
    "name": "USDT",
    "price": 0.999348,
    "change": -0.01181
  },
  {
    "name": "BNB",
    "price": 836.57,
    "change": -0.41479
  },
  {
    "name": "XRP",
    "price": 1.86,
    "change": -0.60502
  },
  {
    "name": "USDC",
    "price": 0.999986,
    "change": -0.0278
  },
  {
    "name": "SOL",
    "price": 122.39,
    "change": -0.60673
  },
  {
    "name": "TRX",
    "price": 0.278491,
    "change": -0.07919
  },
  {
    "name": "STETH",
    "price": 2932.02,
    "change": -0.47695
  },
  {
    "name": "DOGE",
    "price": 0.122306,
    "change": -3.62825
  }
]