[
  {
    "name": "BTC",
    "price": 108355,
    "change": 0.32142
  },
  {
    "name": "ETH",
    "price": 3867.65,
    "change": -0.36543
  },
  {
    "name": "USDT",
    "price": 1.001,
    "change": 0.01288
  },
  {
    "name": "BNB",
    "price": 1069.54,
    "change": -0.21325
  },
  {
    "name": "XRP",
    "price": 2.41,
    "change": -1.02605
  },
  {
    "name": "SOL",
    "price": 184.59,
    "change": -0.08395
  },
  {
    "name": "USDC",
    "price": 0.999746,
    "change": -0.00432
  },
  {
    "name": "STETH",
    "price": 3863.74,
    "change": -0.36816
  },
  {
    "name": "TRX",
    "price": 0.323443,
    "change": 1.38097
  },
  {
    "name": "DOGE",
    "price": 0.191801,
    "change": -1.20426
  }
]