[
  {
    "name": "BTC",
    "price": 88104,
    "change": -0.22839
  },
  {
    "name": "ETH",
    "price": 2981.19,
    "change": -0.35868
  },
  {
    "name": "USDT",
    "price": 0.999646,
    "change": -0.01659
  },
  {
    "name": "BNB",
    "price": 857.97,
    "change": 0.30531
  },
  {
    "name": "XRP",
    "price": 1.9,
    "change": -0.52104
  },
  {
    "name": "USDC",
    "price": 0.999795,
    "change": -0.0311
  },
  {
    "name": "SOL",
    "price": 124.97,
    "change": -0.53884
  },
  {
    "name": "TRX",
    "price": 0.284396,
    "change": -1.29551
  },
  {
    "name": "STETH",
    "price": 2981.35,
    "change": -0.34199
  },
  {
    "name": "DOGE",
    "price": 0.132198,
    "change": 1.56798
  }
]