[
  {
    "name": "BTC",
    "price": 115079,
    "change": -1.46623
  },
  {
    "name": "ETH",
    "price": 4753.87,
    "change": -1.16375
  },
  {
    "name": "XRP",
    "price": 3.03,
    "change": -1.97995
  },
  {
    "name": "USDT",
    "price": 0.999664,
    "change": -0.02423
  },
  {
    "name": "BNB",
    "price": 882.11,
    "change": -1.40148
  },
  {
    "name": "SOL",
    "price": 204.03,
    "change": 3.42321
  },
  {
    "name": "USDC",
    "price": 0.999804,
    "change": -0.00974
  },
  {
    "name": "STETH",
    "price": 4744.55,
    "change": -1.1677
  },
  {
    "name": "DOGE",
    "price": 0.236939,
    "change": -0.62741
  },
  {
    "name": "TRX",
    "price": 0.36108,
    "change": -1.15719
  }
]