[
  {
    "name": "BTC",
    "price": 96036,
    "change": 0.79396
  },
  {
    "name": "ETH",
    "price": 3208.49,
    "change": 0.9501
  },
  {
    "name": "USDT",
    "price": 0.999625,
    "change": 0.02852
  },
  {
    "name": "XRP",
    "price": 2.26,
    "change": -1.05375
  },
  {
    "name": "BNB",
    "price": 942.84,
    "change": 1.95471
  },
  {
    "name": "SOL",
    "price": 142.67,
    "change": 0.55403
  },
  {
    "name": "USDC",
    "price": 0.999721,
    "change": -0.006
  },
  {
    "name": "TRX",
    "price": 0.293081,
    "change": -0.72015
  },
  {
    "name": "STETH",
    "price": 3208.24,
    "change": 1.17628
  },
  {
    "name": "DOGE",
    "price": 0.163794,
    "change": 1.34204
  }
]