[
  {
    "name": "BTC",
    "price": 70758,
    "change": 4.60862
  },
  {
    "name": "ETH",
    "price": 2059.81,
    "change": 3.45062
  },
  {
    "name": "USDT",
    "price": 0.999994,
    "change": 0.02026
  },
  {
    "name": "BNB",
    "price": 645.63,
    "change": 3.32411
  },
  {
    "name": "XRP",
    "price": 1.4,
    "change": 4.31683
  },
  {
    "name": "USDC",
    "price": 0.999997,
    "change": 0.0094
  },
  {
    "name": "SOL",
    "price": 86.75,
    "change": 3.7162
  },
  {
    "name": "TRX",
    "price": 0.28578,
    "change": -0.71165
  },
  {
    "name": "FIGR_HELOC",
    "price": 1.042,
    "change": -0.71835
  },
  {
    "name": "DOGE",
    "price": 0.093637,
    "change": 3.75649
  }
]