[
  {
    "name": "BTC",
    "price": 117896,
    "change": -1.12713
  },
  {
    "name": "ETH",
    "price": 3639.74,
    "change": -4.28789
  },
  {
    "name": "XRP",
    "price": 3.44,
    "change": -3.72453
  },
  {
    "name": "USDT",
    "price": 1.0,
    "change": 0.01034
  },
  {
    "name": "SOL",
    "price": 195.79,
    "change": 2.24512
  },
  {
    "name": "BNB",
    "price": 752.11,
    "change": -1.47276
  },
  {
    "name": "USDC",
    "price": 0.999851,
    "change": -0.00522
  },
  {
    "name": "DOGE",
    "price": 0.265306,
    "change": -4.57617
  },
  {
    "name": "STETH",
    "price": 3631.8,
    "change": -4.22165
  },
  {
    "name": "ADA",
    "price": 0.859626,
    "change": -4.53368
  }
]