[
  {
    "name": "BTC",
    "price": 93467,
    "change": 0.29944
  },
  {
    "name": "ETH",
    "price": 3204.28,
    "change": 4.84075
  },
  {
    "name": "USDT",
    "price": 1.0,
    "change": -0.00762
  },
  {
    "name": "XRP",
    "price": 2.17,
    "change": -0.49941
  },
  {
    "name": "BNB",
    "price": 912.49,
    "change": 1.27011
  },
  {
    "name": "SOL",
    "price": 143.83,
    "change": 1.16113
  },
  {
    "name": "USDC",
    "price": 0.999803,
    "change": 0.00216
  },
  {
    "name": "STETH",
    "price": 3204.74,
    "change": 4.80448
  },
  {
    "name": "TRX",
    "price": 0.280478,
    "change": 0.28288
  },
  {
    "name": "DOGE",
    "price": 0.150253,
    "change": 0.07073
  }
]