[
  {
    "name": "BTC",
    "price": 85990,
    "change": -0.40984
  },
  {
    "name": "ETH",
    "price": 2795.83,
    "change": -0.72006
  },
  {
    "name": "USDT",
    "price": 0.99966,
    "change": 0.00239
  },
  {
    "name": "XRP",
    "price": 2.04,
    "change": -0.2613
  },
  {
    "name": "BNB",
    "price": 841.75,
    "change": -0.31676
  },
  {
    "name": "USDC",
    "price": 0.9997,
    "change": -4e-05
  },
  {
    "name": "SOL",
    "price": 129.0,
    "change": -0.95559
  },
  {
    "name": "TRX",
    "price": 0.276348,
    "change": 0.41389
  },
  {
    "name": "STETH",
    "price": 2794.38,
    "change": -0.66033
  },
  {
    "name": "DOGE",
    "price": 0.144528,
    "change": 0.68282
  }
]