[
  {
    "name": "BTC",
    "price": 108394,
    "change": 1.94676
  },
  {
    "name": "ETH",
    "price": 2576.96,
    "change": 1.86672
  },
  {
    "name": "USDT",
    "price": 1.0,
    "change": 0.00067
  },
  {
    "name": "XRP",
    "price": 2.29,
    "change": 0.35087
  },
  {
    "name": "BNB",
    "price": 659.1,
    "change": 0.92896
  },
  {
    "name": "SOL",
    "price": 156.17,
    "change": 1.55952
  },
  {
    "name": "USDC",
    "price": 0.999797,
    "change": 0.0028
  },
  {
    "name": "DOGE",
    "price": 0.186906,
    "change": 0.61517
  },
  {
    "name": "TRX",
    "price": 0.285991,
    "change": 0.96615
  },
  {
    "name": "ADA",
    "price": 0.681833,
    "change": 1.32164
  }
]