[
  {
    "name": "BTC",
    "price": 120562,
    "change": 1.49282
  },
  {
    "name": "ETH",
    "price": 4494.17,
    "change": 2.46381
  },
  {
    "name": "XRP",
    "price": 3.04,
    "change": 1.84149
  },
  {
    "name": "USDT",
    "price": 1.001,
    "change": 0.00915
  },
  {
    "name": "BNB",
    "price": 1109.8,
    "change": 6.22583
  },
  {
    "name": "SOL",
    "price": 231.3,
    "change": 2.59429
  },
  {
    "name": "USDC",
    "price": 0.999682,
    "change": -0.01178
  },
  {
    "name": "DOGE",
    "price": 0.256976,
    "change": -0.67157
  },
  {
    "name": "STETH",
    "price": 4490.54,
    "change": 2.38203
  },
  {
    "name": "TRX",
    "price": 0.343182,
    "change": 0.55514
  }
]