[
  {
    "name": "BTC",
    "price": 115504,
    "change": -0.20739
  },
  {
    "name": "ETH",
    "price": 4488.33,
    "change": 0.18146
  },
  {
    "name": "XRP",
    "price": 2.98,
    "change": 0.04926
  },
  {
    "name": "USDT",
    "price": 1.0,
    "change": -0.00057
  },
  {
    "name": "BNB",
    "price": 1046.55,
    "change": 2.47708
  },
  {
    "name": "SOL",
    "price": 237.56,
    "change": -0.42096
  },
  {
    "name": "USDC",
    "price": 0.999704,
    "change": 0.00868
  },
  {
    "name": "DOGE",
    "price": 0.262923,
    "change": -1.17905
  },
  {
    "name": "STETH",
    "price": 4485.03,
    "change": 0.22265
  },
  {
    "name": "TRX",
    "price": 0.344167,
    "change": -0.94132
  }
]