[
  {
    "name": "BTC",
    "price": 106449,
    "change": 4.72243
  },
  {
    "name": "ETH",
    "price": 3622.91,
    "change": 6.42174
  },
  {
    "name": "USDT",
    "price": 0.999821,
    "change": -0.01102
  },
  {
    "name": "XRP",
    "price": 2.54,
    "change": 11.66887
  },
  {
    "name": "BNB",
    "price": 1003.95,
    "change": 1.61699
  },
  {
    "name": "SOL",
    "price": 169.35,
    "change": 6.82855
  },
  {
    "name": "USDC",
    "price": 0.999801,
    "change": 1e-05
  },
  {
    "name": "STETH",
    "price": 3620.77,
    "change": 6.39143
  },
  {
    "name": "DOGE",
    "price": 0.184622,
    "change": 6.3124
  },
  {
    "name": "TRX",
    "price": 0.294391,
    "change": 1.85996
  }
]