[
  {
    "name": "BTC",
    "price": 114094,
    "change": 1.55544
  },
  {
    "name": "ETH",
    "price": 4426.75,
    "change": 2.29477
  },
  {
    "name": "XRP",
    "price": 3.02,
    "change": 1.81588
  },
  {
    "name": "USDT",
    "price": 1.0,
    "change": 0.01632
  },
  {
    "name": "BNB",
    "price": 899.85,
    "change": 1.86571
  },
  {
    "name": "SOL",
    "price": 225.23,
    "change": 2.38083
  },
  {
    "name": "USDC",
    "price": 0.999814,
    "change": 0.00038
  },
  {
    "name": "STETH",
    "price": 4419.72,
    "change": 2.26288
  },
  {
    "name": "DOGE",
    "price": 0.250945,
    "change": 4.43642
  },
  {
    "name": "TRX",
    "price": 0.345466,
    "change": 2.50217
  }
]