[
  {
    "name": "BTC",
    "price": 71622,
    "change": -1.74271
  },
  {
    "name": "ETH",
    "price": 2215.03,
    "change": -1.21267
  },
  {
    "name": "USDT",
    "price": 1.0,
    "change": -0.00786
  },
  {
    "name": "XRP",
    "price": 1.33,
    "change": -1.14632
  },
  {
    "name": "BNB",
    "price": 595.46,
    "change": -1.81857
  },
  {
    "name": "USDC",
    "price": 0.99983,
    "change": -0.01284
  },
  {
    "name": "SOL",
    "price": 82.31,
    "change": -2.34146
  },
  {
    "name": "TRX",
    "price": 0.322196,
    "change": 1.13604
  },
  {
    "name": "FIGR_HELOC",
    "price": 1.04,
    "change": 1.8143
  },
  {
    "name": "DOGE",
    "price": 0.091124,
    "change": -1.87682
  }
]