[
  {
    "name": "BTC",
    "price": 64260,
    "change": 1.10623
  },
  {
    "name": "ETH",
    "price": 1731.61,
    "change": 0.43877
  },
  {
    "name": "USDT",
    "price": 0.998839,
    "change": -0.01917
  },
  {
    "name": "BNB",
    "price": 589.84,
    "change": 0.70863
  },
  {
    "name": "USDC",
    "price": 0.999823,
    "change": 0.00732
  },
  {
    "name": "XRP",
    "price": 1.15,
    "change": 0.08777
  },
  {
    "name": "SOL",
    "price": 74.08,
    "change": 3.57395
  },
  {
    "name": "TRX",
    "price": 0.326707,
    "change": 1.01178
  },
  {
    "name": "FIGR_HELOC",
    "price": 1.034,
    "change": 0.0
  },
  {
    "name": "HYPE",
    "price": 68.33,
    "change": -3.46103
  }
]