[
  {
    "name": "BTC",
    "price": 77661,
    "change": -0.24091
  },
  {
    "name": "ETH",
    "price": 2315.07,
    "change": -0.1553
  },
  {
    "name": "USDT",
    "price": 1.0,
    "change": -0.01434
  },
  {
    "name": "XRP",
    "price": 1.44,
    "change": 0.87551
  },
  {
    "name": "BNB",
    "price": 638.11,
    "change": 0.10301
  },
  {
    "name": "USDC",
    "price": 0.999795,
    "change": -0.00723
  },
  {
    "name": "SOL",
    "price": 86.35,
    "change": 0.94147
  },
  {
    "name": "TRX",
    "price": 0.324104,
    "change": -1.53194
  },
  {
    "name": "FIGR_HELOC",
    "price": 1.031,
    "change": -0.46952
  },
  {
    "name": "DOGE",
    "price": 0.09803,
    "change": 1.43966
  }
]