[
  {
    "name": "BTC",
    "price": 106787,
    "change": -0.70011
  },
  {
    "name": "ETH",
    "price": 3863.4,
    "change": 0.75662
  },
  {
    "name": "USDT",
    "price": 1.001,
    "change": 0.0136
  },
  {
    "name": "BNB",
    "price": 1096.34,
    "change": -1.36514
  },
  {
    "name": "XRP",
    "price": 2.34,
    "change": 1.69133
  },
  {
    "name": "SOL",
    "price": 185.41,
    "change": 1.17416
  },
  {
    "name": "USDC",
    "price": 0.999804,
    "change": -0.00741
  },
  {
    "name": "STETH",
    "price": 3861.93,
    "change": 0.62423
  },
  {
    "name": "TRX",
    "price": 0.312536,
    "change": -0.65419
  },
  {
    "name": "DOGE",
    "price": 0.186513,
    "change": 0.27475
  }
]