[
  {
    "name": "BTC",
    "price": 71295,
    "change": 3.67535
  },
  {
    "name": "ETH",
    "price": 2233.53,
    "change": 5.98819
  },
  {
    "name": "USDT",
    "price": 0.999866,
    "change": -0.00414
  },
  {
    "name": "XRP",
    "price": 1.37,
    "change": 4.0676
  },
  {
    "name": "BNB",
    "price": 614.56,
    "change": 2.67552
  },
  {
    "name": "USDC",
    "price": 0.999814,
    "change": 0.00393
  },
  {
    "name": "SOL",
    "price": 84.48,
    "change": 5.90019
  },
  {
    "name": "TRX",
    "price": 0.31549,
    "change": -0.2909
  },
  {
    "name": "FIGR_HELOC",
    "price": 1.033,
    "change": 1.32205
  },
  {
    "name": "DOGE",
    "price": 0.094571,
    "change": 4.45517
  }
]