[
  {
    "name": "BTC",
    "price": 96190,
    "change": -0.44961
  },
  {
    "name": "ETH",
    "price": 3350.11,
    "change": 0.20926
  },
  {
    "name": "USDT",
    "price": 0.999626,
    "change": -0.00969
  },
  {
    "name": "BNB",
    "price": 938.24,
    "change": -0.30182
  },
  {
    "name": "XRP",
    "price": 2.1,
    "change": -2.57726
  },
  {
    "name": "SOL",
    "price": 143.97,
    "change": -1.68673
  },
  {
    "name": "USDC",
    "price": 0.999731,
    "change": -0.01622
  },
  {
    "name": "STETH",
    "price": 3347.05,
    "change": 0.15784
  },
  {
    "name": "TRX",
    "price": 0.30726,
    "change": 1.5289
  },
  {
    "name": "DOGE",
    "price": 0.142718,
    "change": -3.62128
  }
]