[
  {
    "name": "BTC",
    "price": 90188,
    "change": 2.60181
  },
  {
    "name": "ETH",
    "price": 3035.14,
    "change": 4.35616
  },
  {
    "name": "USDT",
    "price": 0.998656,
    "change": -0.00641
  },
  {
    "name": "BNB",
    "price": 905.89,
    "change": 2.72978
  },
  {
    "name": "XRP",
    "price": 1.93,
    "change": 2.77676
  },
  {
    "name": "SOL",
    "price": 127.22,
    "change": 3.18621
  },
  {
    "name": "USDC",
    "price": 0.999623,
    "change": -0.00091
  },
  {
    "name": "STETH",
    "price": 3033.88,
    "change": 4.30948
  },
  {
    "name": "TRX",
    "price": 0.292019,
    "change": -0.47809
  },
  {
    "name": "DOGE",
    "price": 0.126199,
    "change": 3.54549
  }
]