[
  {
    "name": "BTC",
    "price": 109456,
    "change": -0.50991
  },
  {
    "name": "ETH",
    "price": 2600.2,
    "change": 0.69293
  },
  {
    "name": "USDT",
    "price": 1.0,
    "change": -0.01759
  },
  {
    "name": "XRP",
    "price": 2.3,
    "change": -2.18425
  },
  {
    "name": "BNB",
    "price": 680.01,
    "change": 0.86599
  },
  {
    "name": "SOL",
    "price": 175.19,
    "change": -1.58441
  },
  {
    "name": "USDC",
    "price": 0.999713,
    "change": -0.00273
  },
  {
    "name": "DOGE",
    "price": 0.22722,
    "change": -1.09059
  },
  {
    "name": "ADA",
    "price": 0.763923,
    "change": -1.09081
  },
  {
    "name": "TRX",
    "price": 0.27671,
    "change": 1.64581
  }
]