[
  {
    "name": "BTC",
    "price": 107209,
    "change": -0.87063
  },
  {
    "name": "ETH",
    "price": 3866.48,
    "change": -0.15315
  },
  {
    "name": "USDT",
    "price": 1.001,
    "change": 0.00736
  },
  {
    "name": "BNB",
    "price": 1083.6,
    "change": -6.68431
  },
  {
    "name": "XRP",
    "price": 2.33,
    "change": 0.75517
  },
  {
    "name": "SOL",
    "price": 184.52,
    "change": -0.16539
  },
  {
    "name": "USDC",
    "price": 0.999804,
    "change": -0.00937
  },
  {
    "name": "STETH",
    "price": 3863.04,
    "change": -0.15765
  },
  {
    "name": "TRX",
    "price": 0.309758,
    "change": -1.78559
  },
  {
    "name": "DOGE",
    "price": 0.186644,
    "change": -0.34027
  }
]