[
  {
    "name": "BTC",
    "price": 61943,
    "change": 0.67502
  },
  {
    "name": "ETH",
    "price": 1735.19,
    "change": 4.48208
  },
  {
    "name": "USDT",
    "price": 0.998805,
    "change": -0.00019
  },
  {
    "name": "BNB",
    "price": 564.4,
    "change": 0.38891
  },
  {
    "name": "USDC",
    "price": 0.999935,
    "change": 0.01143
  },
  {
    "name": "XRP",
    "price": 1.11,
    "change": 1.28716
  },
  {
    "name": "SOL",
    "price": 81.45,
    "change": 0.22775
  },
  {
    "name": "TRX",
    "price": 0.320098,
    "change": 1.00145
  },
  {
    "name": "FIGR_HELOC",
    "price": 1.039,
    "change": 0.28948
  },
  {
    "name": "HYPE",
    "price": 69.07,
    "change": 5.95219
  }
]