[
  {
    "name": "BTC",
    "price": 109964,
    "change": 2.76555
  },
  {
    "name": "ETH",
    "price": 3893.98,
    "change": 4.43643
  },
  {
    "name": "USDT",
    "price": 0.99956,
    "change": -0.04853
  },
  {
    "name": "XRP",
    "price": 2.52,
    "change": 4.47907
  },
  {
    "name": "BNB",
    "price": 1088.07,
    "change": 2.41005
  },
  {
    "name": "SOL",
    "price": 187.37,
    "change": 3.64175
  },
  {
    "name": "USDC",
    "price": 0.999707,
    "change": -0.00045
  },
  {
    "name": "STETH",
    "price": 3885.94,
    "change": 4.27437
  },
  {
    "name": "DOGE",
    "price": 0.186442,
    "change": 5.07198
  },
  {
    "name": "TRX",
    "price": 0.295875,
    "change": 1.95348
  }
]