[
  {
    "name": "BTC",
    "price": 116650,
    "change": 1.91992
  },
  {
    "name": "ETH",
    "price": 3904.29,
    "change": 6.38224
  },
  {
    "name": "XRP",
    "price": 3.34,
    "change": 12.18188
  },
  {
    "name": "USDT",
    "price": 1.0,
    "change": -0.0068
  },
  {
    "name": "BNB",
    "price": 785.39,
    "change": 2.44067
  },
  {
    "name": "SOL",
    "price": 174.46,
    "change": 4.31523
  },
  {
    "name": "USDC",
    "price": 0.999785,
    "change": -0.00052
  },
  {
    "name": "STETH",
    "price": 3897.34,
    "change": 6.13824
  },
  {
    "name": "DOGE",
    "price": 0.220706,
    "change": 7.87765
  },
  {
    "name": "TRX",
    "price": 0.338439,
    "change": -0.12223
  }
]