[
  {
    "name": "BTC",
    "price": 118290,
    "change": -0.9287
  },
  {
    "name": "ETH",
    "price": 3562.65,
    "change": -1.78951
  },
  {
    "name": "XRP",
    "price": 3.42,
    "change": -2.46551
  },
  {
    "name": "USDT",
    "price": 1.0,
    "change": 0.02797
  },
  {
    "name": "BNB",
    "price": 741.58,
    "change": -1.10402
  },
  {
    "name": "SOL",
    "price": 177.38,
    "change": -1.50348
  },
  {
    "name": "USDC",
    "price": 0.999901,
    "change": -0.00031
  },
  {
    "name": "DOGE",
    "price": 0.246951,
    "change": 0.70563
  },
  {
    "name": "STETH",
    "price": 3555.59,
    "change": -1.8278
  },
  {
    "name": "TRX",
    "price": 0.32653,
    "change": -1.86003
  }
]