[
  {
    "name": "BTC",
    "price": 118381,
    "change": 0.80494
  },
  {
    "name": "ETH",
    "price": 3778.35,
    "change": 1.0168
  },
  {
    "name": "XRP",
    "price": 3.21,
    "change": 1.52761
  },
  {
    "name": "USDT",
    "price": 1.0,
    "change": 0.00833
  },
  {
    "name": "BNB",
    "price": 797.12,
    "change": 1.83539
  },
  {
    "name": "SOL",
    "price": 187.61,
    "change": 0.78222
  },
  {
    "name": "USDC",
    "price": 0.999801,
    "change": -0.00996
  },
  {
    "name": "DOGE",
    "price": 0.239435,
    "change": 0.79429
  },
  {
    "name": "STETH",
    "price": 3775.54,
    "change": 1.03931
  },
  {
    "name": "TRX",
    "price": 0.3216,
    "change": 1.08594
  }
]