[
  {
    "name": "BTC",
    "price": 113348,
    "change": -1.94244
  },
  {
    "name": "ETH",
    "price": 4168.24,
    "change": -3.23292
  },
  {
    "name": "XRP",
    "price": 2.87,
    "change": -4.83603
  },
  {
    "name": "USDT",
    "price": 0.999934,
    "change": -0.03527
  },
  {
    "name": "BNB",
    "price": 828.2,
    "change": -2.11304
  },
  {
    "name": "SOL",
    "price": 178.9,
    "change": -1.85783
  },
  {
    "name": "USDC",
    "price": 0.999801,
    "change": -4e-05
  },
  {
    "name": "STETH",
    "price": 4155.27,
    "change": -3.13755
  },
  {
    "name": "TRX",
    "price": 0.348965,
    "change": -0.67475
  },
  {
    "name": "DOGE",
    "price": 0.211949,
    "change": -3.46904
  }
]