[
  {
    "name": "BTC",
    "price": 111056,
    "change": -2.48528
  },
  {
    "name": "ETH",
    "price": 3936.99,
    "change": -3.04433
  },
  {
    "name": "USDT",
    "price": 1.0,
    "change": 0.02789
  },
  {
    "name": "XRP",
    "price": 2.62,
    "change": -1.05372
  },
  {
    "name": "BNB",
    "price": 1110.23,
    "change": -2.23684
  },
  {
    "name": "SOL",
    "price": 194.38,
    "change": -1.66276
  },
  {
    "name": "USDC",
    "price": 0.999804,
    "change": 0.00188
  },
  {
    "name": "STETH",
    "price": 3939.93,
    "change": -3.00864
  },
  {
    "name": "DOGE",
    "price": 0.194766,
    "change": -1.65976
  },
  {
    "name": "TRX",
    "price": 0.296315,
    "change": -0.53612
  }
]