[
  {
    "name": "BTC",
    "price": 112179,
    "change": -4.97071
  },
  {
    "name": "ETH",
    "price": 3827.92,
    "change": -6.72341
  },
  {
    "name": "USDT",
    "price": 1.001,
    "change": 0.09503
  },
  {
    "name": "BNB",
    "price": 1175.67,
    "change": -3.98985
  },
  {
    "name": "XRP",
    "price": 2.48,
    "change": -8.79054
  },
  {
    "name": "SOL",
    "price": 184.05,
    "change": -12.58103
  },
  {
    "name": "USDC",
    "price": 0.999805,
    "change": -0.00085
  },
  {
    "name": "STETH",
    "price": 3825.28,
    "change": -6.76385
  },
  {
    "name": "TRX",
    "price": 0.319858,
    "change": -3.53764
  },
  {
    "name": "DOGE",
    "price": 0.19283,
    "change": -18.37838
  }
]