[
  {
    "name": "BTC",
    "price": 112376,
    "change": -1.63538
  },
  {
    "name": "ETH",
    "price": 4233.04,
    "change": -2.65661
  },
  {
    "name": "XRP",
    "price": 2.87,
    "change": -3.33891
  },
  {
    "name": "USDT",
    "price": 0.999746,
    "change": -0.02435
  },
  {
    "name": "BNB",
    "price": 837.46,
    "change": -4.1322
  },
  {
    "name": "SOL",
    "price": 180.36,
    "change": -3.50757
  },
  {
    "name": "USDC",
    "price": 0.999708,
    "change": -0.00187
  },
  {
    "name": "STETH",
    "price": 4220.54,
    "change": -2.74496
  },
  {
    "name": "TRX",
    "price": 0.353805,
    "change": 0.00713
  },
  {
    "name": "DOGE",
    "price": 0.215264,
    "change": -2.73698
  }
]