[
  {
    "name": "BTC",
    "price": 118013,
    "change": 4.57565
  },
  {
    "name": "ETH",
    "price": 4334.54,
    "change": 5.64538
  },
  {
    "name": "XRP",
    "price": 2.95,
    "change": 4.2379
  },
  {
    "name": "USDT",
    "price": 1.001,
    "change": 0.05931
  },
  {
    "name": "BNB",
    "price": 1019.74,
    "change": 1.88097
  },
  {
    "name": "SOL",
    "price": 220.26,
    "change": 7.44325
  },
  {
    "name": "USDC",
    "price": 0.999615,
    "change": 0.00268
  },
  {
    "name": "DOGE",
    "price": 0.245489,
    "change": 7.7816
  },
  {
    "name": "STETH",
    "price": 4332.44,
    "change": 5.51237
  },
  {
    "name": "TRX",
    "price": 0.340592,
    "change": 2.17782
  }
]