[
  {
    "name": "BTC",
    "price": 67273,
    "change": -1.41933
  },
  {
    "name": "ETH",
    "price": 1962.54,
    "change": -1.17185
  },
  {
    "name": "USDT",
    "price": 0.999954,
    "change": -0.00509
  },
  {
    "name": "BNB",
    "price": 620.36,
    "change": -1.7509
  },
  {
    "name": "XRP",
    "price": 1.35,
    "change": -0.69344
  },
  {
    "name": "USDC",
    "price": 0.999919,
    "change": -0.00789
  },
  {
    "name": "SOL",
    "price": 82.95,
    "change": -3.0508
  },
  {
    "name": "TRX",
    "price": 0.286044,
    "change": 0.34902
  },
  {
    "name": "FIGR_HELOC",
    "price": 1.018,
    "change": -1.60509
  },
  {
    "name": "DOGE",
    "price": 0.08983,
    "change": -1.1757
  }
]