[
  {
    "name": "BTC",
    "price": 86411,
    "change": 0.05866
  },
  {
    "name": "ETH",
    "price": 2926.34,
    "change": -0.17303
  },
  {
    "name": "USDT",
    "price": 0.999842,
    "change": -0.0072
  },
  {
    "name": "BNB",
    "price": 864.21,
    "change": 0.3872
  },
  {
    "name": "XRP",
    "price": 1.9,
    "change": 1.25622
  },
  {
    "name": "USDC",
    "price": 1.0,
    "change": 0.01925
  },
  {
    "name": "SOL",
    "price": 126.59,
    "change": 0.20678
  },
  {
    "name": "TRX",
    "price": 0.279112,
    "change": -0.07891
  },
  {
    "name": "STETH",
    "price": 2924.68,
    "change": -0.1257
  },
  {
    "name": "DOGE",
    "price": 0.129748,
    "change": 0.66225
  }
]