[
  {
    "name": "BTC",
    "price": 102497,
    "change": -1.34652
  },
  {
    "name": "ETH",
    "price": 2261.13,
    "change": -7.23413
  },
  {
    "name": "USDT",
    "price": 1.0,
    "change": 0.00354
  },
  {
    "name": "XRP",
    "price": 2.04,
    "change": -4.49993
  },
  {
    "name": "BNB",
    "price": 629.38,
    "change": -1.85643
  },
  {
    "name": "SOL",
    "price": 133.49,
    "change": -5.99761
  },
  {
    "name": "USDC",
    "price": 0.999772,
    "change": -0.00294
  },
  {
    "name": "TRX",
    "price": 0.272152,
    "change": -0.72942
  },
  {
    "name": "DOGE",
    "price": 0.15537,
    "change": -5.0585
  },
  {
    "name": "STETH",
    "price": 2260.65,
    "change": -7.19712
  }
]