[
  {
    "name": "BTC",
    "price": 107567,
    "change": 0.68701
  },
  {
    "name": "ETH",
    "price": 3915.44,
    "change": 1.07443
  },
  {
    "name": "USDT",
    "price": 1.0,
    "change": -0.02881
  },
  {
    "name": "BNB",
    "price": 1090.59,
    "change": -1.42269
  },
  {
    "name": "XRP",
    "price": 2.35,
    "change": -0.06091
  },
  {
    "name": "SOL",
    "price": 186.43,
    "change": 0.38857
  },
  {
    "name": "USDC",
    "price": 0.999856,
    "change": -0.00415
  },
  {
    "name": "STETH",
    "price": 3911.27,
    "change": 0.89638
  },
  {
    "name": "TRX",
    "price": 0.31553,
    "change": 0.7728
  },
  {
    "name": "DOGE",
    "price": 0.189416,
    "change": 1.01875
  }
]