[
  {
    "name": "BTC",
    "price": 87895,
    "change": 0.74341
  },
  {
    "name": "ETH",
    "price": 2981.88,
    "change": 1.8397
  },
  {
    "name": "USDT",
    "price": 0.998851,
    "change": -0.01006
  },
  {
    "name": "BNB",
    "price": 857.12,
    "change": 0.87126
  },
  {
    "name": "XRP",
    "price": 1.86,
    "change": -0.02803
  },
  {
    "name": "USDC",
    "price": 0.999863,
    "change": 0.00558
  },
  {
    "name": "SOL",
    "price": 124.1,
    "change": 0.32841
  },
  {
    "name": "TRX",
    "price": 0.28518,
    "change": 1.31733
  },
  {
    "name": "STETH",
    "price": 2981.64,
    "change": 1.85739
  },
  {
    "name": "DOGE",
    "price": 0.123807,
    "change": 0.33044
  }
]