[
  {
    "name": "BTC",
    "price": 113453,
    "change": 1.47808
  },
  {
    "name": "ETH",
    "price": 4161.04,
    "change": -0.042
  },
  {
    "name": "XRP",
    "price": 2.95,
    "change": 3.03297
  },
  {
    "name": "USDT",
    "price": 1.0,
    "change": 0.00132
  },
  {
    "name": "BNB",
    "price": 1015.65,
    "change": 0.37569
  },
  {
    "name": "SOL",
    "price": 213.11,
    "change": -1.3549
  },
  {
    "name": "USDC",
    "price": 0.999705,
    "change": 0.00667
  },
  {
    "name": "DOGE",
    "price": 0.243855,
    "change": 1.93087
  },
  {
    "name": "STETH",
    "price": 4157.88,
    "change": -0.21564
  },
  {
    "name": "TRX",
    "price": 0.339011,
    "change": 0.86067
  }
]